README.md
incipit/__init__.py
incipit/cli.py
incipit/heuristics.py
incipit/processing.py
incipit-2021.3.2.dist-info/entry_points.txt
incipit-2021.3.2.dist-info/LICENSE
incipit-2021.3.2.dist-info/WHEEL
incipit-2021.3.2.dist-info/METADATA
incipit-2021.3.2.dist-info/RECORD
