Metadata-Version: 2.1
Name: incipit
Version: 2021.3.2
Summary: CLI and Python package to extract systems of staves from musical scores.
Home-page: https://github.com/jlumbroso/incipit
License: LGPL-3.0-or-later
Keywords: command-line tool,image processing,musical score
Author: Jérémie Lumbroso
Author-email: lumbroso@cs.princeton.edu
Requires-Python: >=3.8,<4.0
Classifier: Development Status :: 4 - Beta
Classifier: License :: OSI Approved :: GNU Lesser General Public License v3 or later (LGPLv3+)
Classifier: Programming Language :: Python :: 3
Classifier: Programming Language :: Python :: 3.8
Classifier: Programming Language :: Python :: 3.9
Classifier: Topic :: Scientific/Engineering :: Image Processing
Classifier: Topic :: Software Development :: Libraries :: Python Modules
Requires-Dist: PyPDF4 (>=1.27.0,<2.0.0)
Requires-Dist: click (>=7.1.2,<8.0.0)
Requires-Dist: click_help_colors (>=0.9,<0.10)
Requires-Dist: loguru (>=0.5.3,<0.6.0)
Requires-Dist: opencv-python (>=4.5.1,<5.0.0)
Requires-Dist: pillow (>=8.1.2,<9.0.0)
Project-URL: Repository, https://github.com/jlumbroso/incipit
